simple_profile/__init__.py
simple_profile/decorators.py
simple_profile/types.py
simple_profile/utils.py
simple_profile-2.0.0.dist-info/LICENSE
simple_profile-2.0.0.dist-info/METADATA
simple_profile-2.0.0.dist-info/WHEEL
simple_profile-2.0.0.dist-info/RECORD
