Metadata-Version: 2.3
Name: simple-profile
Version: 2.0.0
Summary: Simple decorators to profile the memory usage and execution time.
License: GPL-3.0-only
Keywords: profiler,profiling,timer,timing,timeit,tracemalloc,memory,execution,decorator
Author: João Brilhante
Requires-Python: >=3.9
Classifier: Development Status :: 4 - Beta
Classifier: Environment :: Console
Classifier: Intended Audience :: Developers
Classifier: License :: OSI Approved :: GNU General Public License v3 (GPLv3)
Classifier: Operating System :: OS Independent
Classifier: Programming Language :: Python :: 3
Classifier: Programming Language :: Python :: 3.9
Classifier: Programming Language :: Python :: 3.10
Classifier: Programming Language :: Python :: 3.11
Classifier: Programming Language :: Python :: 3.12
Classifier: Programming Language :: Python :: 3.13
Classifier: Topic :: Software Development :: Debuggers
Classifier: Topic :: Software Development :: Libraries
Classifier: Topic :: Software Development :: Testing
Classifier: Topic :: System :: Monitoring
Classifier: Typing :: Typed
Project-URL: Homepage, https://github.com/JoaoBrlt/simple-profile
Project-URL: Repository, https://github.com/JoaoBrlt/simple-profile
